karen/__init__.py
karen/inspection.py
karen/orders.py
karen_inspect-0.1.0.dist-info/LICENSE
karen_inspect-0.1.0.dist-info/METADATA
karen_inspect-0.1.0.dist-info/WHEEL
karen_inspect-0.1.0.dist-info/entry_points.txt
karen_inspect-0.1.0.dist-info/top_level.txt
karen_inspect-0.1.0.dist-info/RECORD
