Metadata-Version: 2.1
Name: karen-inspect
Version: 0.1.0
Summary: A Python linter that flags "naughty" words and non-inclusive language to ensure code is HR compliant
Home-page: https://github.com/amshamah419/Karen-Inspect
Author: Amichai Shamah
Author-email: amshamah@gmail.com
Classifier: Programming Language :: Python :: 3
Classifier: License :: OSI Approved :: MIT License
Classifier: Operating System :: OS Independent
Requires-Python: >=3.6
License-File: LICENSE
Requires-Dist: click
